{
  "ABI": {
    "name": "ABI",
    "region": "AFRICA West",
    "country": "Côte D'Ivoire",
    "country_iso3": "CIV",
    "smt_assignmentgroup": "ABI ICT L2 SUPPORT",
    "latitude": null,
    "longitude": null,
    "source": "grafana_fortigate_labels",
    "sub_sites": [
      "CTN",
      "DAP",
      "LOM"
    ]
  },
  "ABJ": {
    "name": "ABJ",
    "region": "AFRICA West",
    "country": "Cote d'Ivoire",
    "country_iso3": "CIV",
    "smt_assignmentgroup": "ABJ ICT L2 SUPPORT",
    "latitude": null,
    "longitude": null,
    "source": "grafana_fortigate_labels",
    "sub_sites": [
      "BIU",
      "ID1",
      "YOL"
    ]
  },
  "ADD": {
    "name": "ADD",
    "region": "AFRICA East",
    "country": "Ethiopia",
    "country_iso3": "ETH",
    "smt_assignmentgroup": "ADD ICT L2 SUPPORT",
    "latitude": null,
    "longitude": null,
    "source": "grafana_fortigate_labels",
    "sub_sites": [
      "AD2",
      "BAH",
      "JIJ",
      "NEK"
    ]
  },
  "ADE": {
    "name": "ADE",
    "region": "NAME",
    "country": "Yemen",
    "country_iso3": "YEM",
    "smt_assignmentgroup": "ADE ICT L2 SUPPORT",
    "latitude": null,
    "longitude": null,
    "source": "grafana_fortigate_labels",
    "sub_sites": [
      "RADE10",
      "RADE11",
      "WADE12",
      "WADE2"
    ]
  },
  "ADR": {
    "name": "ADR",
    "region": "AFRICA West",
    "country": null,
    "country_iso3": null,
    "smt_assignmentgroup": "ADR ICT L2 SUPPORT",
    "latitude": null,
    "longitude": null,
    "source": "grafana_fortigate_labels",
    "sub_sites": [
      "RADR02"
    ]
  },
  "AFC": {
    "name": "AFC",
    "region": "ASIA",
    "country": null,
    "country_iso3": null,
    "smt_assignmentgroup": "AFC ICT L2 SUPPORT",
    "latitude": null,
    "longitude": null,
    "source": "grafana_fortigate_labels",
    "sub_sites": [
      "GUL",
      "JA1",
      "JAL",
      "KHS",
      "OGUL1",
      "RAFC4"
    ]
  },
  "ALO": {
    "name": "ALO",
    "region": "NAME",
    "country": null,
    "country_iso3": null,
    "smt_assignmentgroup": "ALO ICT L2 SUPPORT",
    "latitude": null,
    "longitude": null,
    "source": "grafana_fortigate_labels",
    "sub_sites": []
  },
  "AMM": {
    "name": "AMM",
    "region": "NAME",
    "country": "Jordan",
    "country_iso3": "JOR",
    "smt_assignmentgroup": "AMM ICT L2 Support",
    "latitude": null,
    "longitude": null,
    "source": "grafana_fortigate_labels",
    "sub_sites": [
      "AM1",
      "AMW"
    ]
  },
  "APP": {
    "name": "APP",
    "region": "HQ",
    "country": null,
    "country_iso3": null,
    "smt_assignmentgroup": "TI GVA Proximity Infra",
    "latitude": null,
    "longitude": null,
    "source": "grafana_fortigate_labels",
    "sub_sites": []
  },
  "BAG": {
    "name": "BAG",
    "region": "NAME",
    "country": "Iraq",
    "country_iso3": "IRQ",
    "smt_assignmentgroup": "BAG ICT L2 SUPPORT",
    "latitude": null,
    "longitude": null,
    "source": "grafana_fortigate_labels",
    "sub_sites": [
      "RRAD11",
      "WBAG30"
    ]
  },
  "BAM": {
    "name": "BAM",
    "region": "AFRICA West",
    "country": "Mali",
    "country_iso3": "MLI",
    "smt_assignmentgroup": "BAM ICT L2 SUPPORT",
    "latitude": null,
    "longitude": null,
    "source": "grafana_fortigate_labels",
    "sub_sites": [
      "ABAM01"
    ]
  },
  "BAN": {
    "name": "BAN",
    "region": "ASIA",
    "country": "Thailand",
    "country_iso3": "THA",
    "smt_assignmentgroup": "BAN ICT L2 SUPPORT",
    "latitude": null,
    "longitude": null,
    "source": "grafana_fortigate_labels",
    "sub_sites": [
      "BN1",
      "CHM",
      "PPO"
    ]
  },
  "BEH": {
    "name": "BEH",
    "region": "AFRICA West",
    "country": null,
    "country_iso3": null,
    "smt_assignmentgroup": "BEH ICT L2 SUPPORT",
    "latitude": null,
    "longitude": null,
    "source": "grafana_fortigate_labels",
    "sub_sites": []
  },
  "BEJ": {
    "name": "BEJ",
    "region": "ASIA",
    "country": null,
    "country_iso3": null,
    "smt_assignmentgroup": "BEJ ICT L2 SUPPORT",
    "latitude": null,
    "longitude": null,
    "source": "grafana_fortigate_labels",
    "sub_sites": []
  },
  "BEL": {
    "name": "BEL",
    "region": "EURASIA",
    "country": null,
    "country_iso3": null,
    "smt_assignmentgroup": "BEL ICT L2 SUPPORT",
    "latitude": null,
    "longitude": null,
    "source": "grafana_fortigate_labels",
    "sub_sites": [
      "BE1"
    ]
  },
  "BEY": {
    "name": "BEY",
    "region": "NAME",
    "country": "Lebanon",
    "country_iso3": "LBN",
    "smt_assignmentgroup": "BEY ICT L2 Support",
    "latitude": null,
    "longitude": null,
    "source": "grafana_fortigate_labels",
    "sub_sites": [
      "TGH",
      "TYR",
      "ZAA",
      "ZAH"
    ]
  },
  "BNG": {
    "name": "BNG",
    "region": "AFRICA East",
    "country": "Central African Republic",
    "country_iso3": "CAF",
    "smt_assignmentgroup": "BNG ICT L2 SUPPORT",
    "latitude": null,
    "longitude": null,
    "source": "grafana_fortigate_labels",
    "sub_sites": [
      "BIA",
      "BMB",
      "BNG1",
      "BON"
    ]
  },
  "BNI": {
    "name": "BNI",
    "region": "AFRICA East",
    "country": null,
    "country_iso3": null,
    "smt_assignmentgroup": "BNI ICT L2 SUPPORT",
    "latitude": null,
    "longitude": null,
    "source": "grafana_fortigate_labels",
    "sub_sites": []
  },
  "BOG": {
    "name": "BOG",
    "region": "AMERICAS",
    "country": "Colombia",
    "country_iso3": "COL",
    "smt_assignmentgroup": "BOG ICT L2 SUPPORT",
    "latitude": null,
    "longitude": null,
    "source": "grafana_fortigate_labels",
    "sub_sites": [
      "BUA",
      "CUC",
      "FLO",
      "MEE",
      "PUA",
      "QUB",
      "SAA",
      "SAO",
      "TUM"
    ]
  },
  "BRA": {
    "name": "BRA",
    "region": "AMERICAS",
    "country": "Brazil",
    "country_iso3": "BRA",
    "smt_assignmentgroup": "BRA ICT L2 SUPPORT",
    "latitude": null,
    "longitude": null,
    "source": "grafana_fortigate_labels",
    "sub_sites": [
      "FOZ"
    ]
  },
  "BSC": {
    "name": "BSC",
    "region": "EURASIA",
    "country": null,
    "country_iso3": null,
    "smt_assignmentgroup": "BSC ICT L2 SUPPORT",
    "latitude": null,
    "longitude": null,
    "source": "grafana_fortigate_labels",
    "sub_sites": []
  },
  "BUJ": {
    "name": "BUJ",
    "region": "AFRICA East",
    "country": "Burundi",
    "country_iso3": "BDI",
    "smt_assignmentgroup": "BUJ ICT L2 SUPPORT",
    "latitude": null,
    "longitude": null,
    "source": "grafana_fortigate_labels",
    "sub_sites": []
  },
  "BUK": {
    "name": "BUK",
    "region": "AFRICA East",
    "country": "Rdcongo",
    "country_iso3": null,
    "smt_assignmentgroup": "BUK ICT L2 SUPPORT",
    "latitude": null,
    "longitude": null,
    "source": "grafana_fortigate_labels",
    "sub_sites": [
      "ABUK1",
      "ABUK2",
      "UVI"
    ]
  },
  "BUN": {
    "name": "BUN",
    "region": "AFRICA East",
    "country": "Democratic Republic Of The Congo",
    "country_iso3": null,
    "smt_assignmentgroup": "BUN ICT L2 SUPPORT",
    "latitude": null,
    "longitude": null,
    "source": "grafana_fortigate_labels",
    "sub_sites": []
  },
  "CAA": {
    "name": "CAA",
    "region": "AMERICAS",
    "country": null,
    "country_iso3": null,
    "smt_assignmentgroup": "CAA ICT L2 SUPPORT",
    "latitude": null,
    "longitude": null,
    "source": "grafana_fortigate_labels",
    "sub_sites": [
      "PUO",
      "SCI",
      "WCAA52"
    ]
  },
  "CAI": {
    "name": "CAI",
    "region": "NAME",
    "country": null,
    "country_iso3": null,
    "smt_assignmentgroup": "CAI ICT L2 SUPPORT",
    "latitude": null,
    "longitude": null,
    "source": "grafana_fortigate_labels",
    "sub_sites": []
  },
  "COL": {
    "name": "COL",
    "region": "ASIA",
    "country": "Sri Lanka",
    "country_iso3": "LKA",
    "smt_assignmentgroup": "COL ICT L2 SUPPORT",
    "latitude": 39.5500507,
    "longitude": -105.7820674,
    "source": "grafana_fortigate_labels",
    "sub_sites": [
      "BAT"
    ]
  },
  "COT": {
    "name": "COT",
    "region": "ASIA",
    "country": "Benin",
    "country_iso3": "BEN",
    "smt_assignmentgroup": "COT ICT L2 Support",
    "latitude": null,
    "longitude": null,
    "source": "grafana_fortigate_labels",
    "sub_sites": [
      "BILI3",
      "RCOT5"
    ]
  },
  "DAA": {
    "name": "DAA",
    "region": "AFRICA East",
    "country": null,
    "country_iso3": null,
    "smt_assignmentgroup": "DAA ICT L2 SUPPORT",
    "latitude": null,
    "longitude": null,
    "source": "grafana_fortigate_labels",
    "sub_sites": []
  },
  "DAK": {
    "name": "DAK",
    "region": "AFRICA West",
    "country": "Senegal",
    "country_iso3": "SEN",
    "smt_assignmentgroup": "DAK ICT L2 SUPPORT",
    "latitude": null,
    "longitude": null,
    "source": "grafana_fortigate_labels",
    "sub_sites": []
  },
  "DAM": {
    "name": "DAM",
    "region": "NAME",
    "country": "Syria",
    "country_iso3": "SYR",
    "smt_assignmentgroup": "DAM ICT L2 SUPPORT",
    "latitude": null,
    "longitude": null,
    "source": "grafana_fortigate_labels",
    "sub_sites": [
      "DEZ",
      "DSS",
      "HOM",
      "KIW",
      "TLC",
      "WDAM83"
    ]
  },
  "DEL": {
    "name": "DEL",
    "region": "ASIA",
    "country": "India",
    "country_iso3": "IND",
    "smt_assignmentgroup": "DEL ICT L2 SUPPORT",
    "latitude": 38.9108325,
    "longitude": -75.5276699,
    "source": "grafana_fortigate_labels",
    "sub_sites": [
      "JMU",
      "KAT",
      "SRI"
    ]
  },
  "DHA": {
    "name": "DHA",
    "region": "ASIA",
    "country": null,
    "country_iso3": null,
    "smt_assignmentgroup": "DHA ICT L2 Support",
    "latitude": null,
    "longitude": null,
    "source": "grafana_fortigate_labels",
    "sub_sites": [
      "CXB"
    ]
  },
  "DJA": {
    "name": "DJA",
    "region": "ASIA",
    "country": null,
    "country_iso3": null,
    "smt_assignmentgroup": "DJA ICT L2 Support",
    "latitude": null,
    "longitude": null,
    "source": "grafana_fortigate_labels",
    "sub_sites": []
  },
  "DJI": {
    "name": "DJI",
    "region": "AFRICA East",
    "country": "Djibouti",
    "country_iso3": "DJI",
    "smt_assignmentgroup": "DJI ICT L2 Support",
    "latitude": null,
    "longitude": null,
    "source": "grafana_fortigate_labels",
    "sub_sites": []
  },
  "DNI": {
    "name": "DNI",
    "region": "EURASIA",
    "country": "Ukraine",
    "country_iso3": "UKR",
    "smt_assignmentgroup": "DNI ICT L2 SUPPORT",
    "latitude": null,
    "longitude": null,
    "source": "grafana_fortigate_labels",
    "sub_sites": [
      "WDNI17"
    ]
  },
  "DON": {
    "name": "DON",
    "region": "EURASIA",
    "country": null,
    "country_iso3": null,
    "smt_assignmentgroup": "DON ICT L2 SUPPORT",
    "latitude": null,
    "longitude": null,
    "source": "grafana_fortigate_labels",
    "sub_sites": []
  },
  "ERB": {
    "name": "ERB",
    "region": "NAME",
    "country": "Iraq",
    "country_iso3": "IRQ",
    "smt_assignmentgroup": "ERB ICT L2 SUPPORT",
    "latitude": null,
    "longitude": null,
    "source": "grafana_fortigate_labels",
    "sub_sites": [
      "EBA",
      "EBL"
    ]
  },
  "ERE": {
    "name": "ERE",
    "region": "EURASIA",
    "country": null,
    "country_iso3": null,
    "smt_assignmentgroup": "ERE ICT L2 SUPPORT",
    "latitude": null,
    "longitude": null,
    "source": "grafana_fortigate_labels",
    "sub_sites": []
  },
  "GAO": {
    "name": "GAO",
    "region": "AFRICA West",
    "country": "Mali",
    "country_iso3": "MLI",
    "smt_assignmentgroup": "GAO ICT L2 SUPPORT",
    "latitude": null,
    "longitude": null,
    "source": "grafana_fortigate_labels",
    "sub_sites": [
      "MKA"
    ]
  },
  "GAZ": {
    "name": "GAZ",
    "region": "NAME",
    "country": "Palestine",
    "country_iso3": "PSE",
    "smt_assignmentgroup": "GAZ ICT L2 SUPPORT",
    "latitude": null,
    "longitude": null,
    "source": "grafana_fortigate_labels",
    "sub_sites": [
      "AKYO01",
      "AKYO02",
      "AKYO03",
      "AKYO04",
      "AKYO05",
      "KYO"
    ]
  },
  "GOM": {
    "name": "GOM",
    "region": "AFRICA East",
    "country": "Rd Congo",
    "country_iso3": null,
    "smt_assignmentgroup": "GOM ICT L2 SUPPORT",
    "latitude": null,
    "longitude": null,
    "source": "grafana_fortigate_labels",
    "sub_sites": [
      "AGOM2",
      "AGOM3"
    ]
  },
  "GVA": {
    "name": "GVA",
    "region": "HQ",
    "country": "Switzerland",
    "country_iso3": "CHE",
    "smt_assignmentgroup": "TI GVA Proximity Infra",
    "latitude": null,
    "longitude": null,
    "source": "grafana_fortigate_labels",
    "sub_sites": []
  },
  "GVAGRG": {
    "name": "GVAGRG",
    "region": "HQ",
    "country": null,
    "country_iso3": null,
    "smt_assignmentgroup": "TI GVA Proximity Infra",
    "latitude": null,
    "longitude": null,
    "source": "grafana_fortigate_labels",
    "sub_sites": []
  },
  "HAS": {
    "name": "HAS",
    "region": "NAME",
    "country": null,
    "country_iso3": null,
    "smt_assignmentgroup": "HAS ICT L2 SUPPORT",
    "latitude": null,
    "longitude": null,
    "source": "grafana_fortigate_labels",
    "sub_sites": []
  },
  "HER": {
    "name": "HER",
    "region": "ASIA",
    "country": null,
    "country_iso3": null,
    "smt_assignmentgroup": "HER ICT L2 SUPPORT",
    "latitude": null,
    "longitude": null,
    "source": "grafana_fortigate_labels",
    "sub_sites": [
      "HE1"
    ]
  },
  "HOE": {
    "name": "HOE",
    "region": "NAME",
    "country": null,
    "country_iso3": null,
    "smt_assignmentgroup": "HOE ICT L2 SUPPORT",
    "latitude": null,
    "longitude": null,
    "source": "grafana_fortigate_labels",
    "sub_sites": []
  },
  "ISL": {
    "name": "ISL",
    "region": "ASIA",
    "country": "Pakistan",
    "country_iso3": "PAK",
    "smt_assignmentgroup": "ISL ICT L2 SUPPORT",
    "latitude": null,
    "longitude": null,
    "source": "grafana_fortigate_labels",
    "sub_sites": [
      "SEO"
    ]
  },
  "JER": {
    "name": "JER",
    "region": "NAME",
    "country": null,
    "country_iso3": null,
    "smt_assignmentgroup": "JER ICT L2 SUPPORT",
    "latitude": null,
    "longitude": null,
    "source": "grafana_fortigate_labels",
    "sub_sites": [
      "AJER01",
      "ATEL01",
      "BET",
      "HEB",
      "JERWH1",
      "TEL"
    ]
  },
  "JUB": {
    "name": "JUB",
    "region": "AFRICA East",
    "country": "South Sudan",
    "country_iso3": "SSD",
    "smt_assignmentgroup": "JUB ICT L2 SUPPORT",
    "latitude": null,
    "longitude": null,
    "source": "grafana_fortigate_labels",
    "sub_sites": [
      "AKB",
      "LEE",
      "LOL",
      "MAL",
      "WAU",
      "WJUB7",
      "YEI"
    ]
  },
  "KAB": {
    "name": "KAB",
    "region": "ASIA",
    "country": "Afghanistan",
    "country_iso3": "AFG",
    "smt_assignmentgroup": "KAB ICT L2 SUPPORT",
    "latitude": null,
    "longitude": null,
    "source": "grafana_fortigate_labels",
    "sub_sites": [
      "FAI",
      "KA1",
      "KA2",
      "KUD",
      "MZ1"
    ]
  },
  "KAD": {
    "name": "KAD",
    "region": "ASIA",
    "country": "Iraq",
    "country_iso3": "IRQ",
    "smt_assignmentgroup": "KAD ICT L2 Support",
    "latitude": null,
    "longitude": null,
    "source": "grafana_fortigate_labels",
    "sub_sites": []
  },
  "KAM": {
    "name": "KAM",
    "region": "AFRICA East",
    "country": "Uganda",
    "country_iso3": "UGA",
    "smt_assignmentgroup": "KAM ICT L2 Support",
    "latitude": null,
    "longitude": null,
    "source": "grafana_fortigate_labels",
    "sub_sites": []
  },
  "KAS": {
    "name": "KAS",
    "region": "AFRICA East",
    "country": "Sudan",
    "country_iso3": "SDN",
    "smt_assignmentgroup": "KAS ICT L2 SUPPORT",
    "latitude": null,
    "longitude": null,
    "source": "grafana_fortigate_labels",
    "sub_sites": []
  },
  "KDL": {
    "name": "KDL",
    "region": "AFRICA West",
    "country": null,
    "country_iso3": null,
    "smt_assignmentgroup": "KDL ICT L2 SUPPORT",
    "latitude": null,
    "longitude": null,
    "source": "grafana_fortigate_labels",
    "sub_sites": []
  },
  "KHC": {
    "name": "KHC",
    "region": "AFRICA East",
    "country": null,
    "country_iso3": null,
    "smt_assignmentgroup": "KHC ICT L2 SUPPORT",
    "latitude": null,
    "longitude": null,
    "source": "grafana_fortigate_labels",
    "sub_sites": []
  },
  "KHR": {
    "name": "KHR",
    "region": "EURASIA",
    "country": null,
    "country_iso3": null,
    "smt_assignmentgroup": "KHR ICT L2 SUPPORT",
    "latitude": null,
    "longitude": null,
    "source": "grafana_fortigate_labels",
    "sub_sites": []
  },
  "KIG": {
    "name": "KIG",
    "region": "AFRICA East",
    "country": "Rwanda",
    "country_iso3": "RWA",
    "smt_assignmentgroup": "KIG ICT L2 SUPPORT",
    "latitude": null,
    "longitude": null,
    "source": "grafana_fortigate_labels",
    "sub_sites": []
  },
  "KIN": {
    "name": "KIN",
    "region": "AFRICA East",
    "country": "Rdc",
    "country_iso3": null,
    "smt_assignmentgroup": "KIN ICT L2 SUPPORT",
    "latitude": null,
    "longitude": null,
    "source": "grafana_fortigate_labels",
    "sub_sites": []
  },
  "KOW": {
    "name": "KOW",
    "region": "NAME",
    "country": "Democratic Republic of the Congo",
    "country_iso3": null,
    "smt_assignmentgroup": "KOW ICT L2 SUPPORT",
    "latitude": null,
    "longitude": null,
    "source": "grafana_fortigate_labels",
    "sub_sites": [
      "ABU",
      "DBI",
      "DOA",
      "MUS"
    ]
  },
  "KUA": {
    "name": "KUA",
    "region": "ASIA",
    "country": "Malaysia",
    "country_iso3": "MYS",
    "smt_assignmentgroup": "KUA ICT L2 SUPPORT",
    "latitude": null,
    "longitude": null,
    "source": "grafana_fortigate_labels",
    "sub_sites": []
  },
  "KYI": {
    "name": "KYI",
    "region": "EURASIA",
    "country": "Ukraine",
    "country_iso3": "UKR",
    "smt_assignmentgroup": "KYI ICT L2 SUPPORT",
    "latitude": null,
    "longitude": null,
    "source": "grafana_fortigate_labels",
    "sub_sites": [
      "BKYI02",
      "KYN",
      "KYR",
      "LVI",
      "ODEVHF",
      "WKYI4"
    ]
  },
  "LAK": {
    "name": "LAK",
    "region": "ASIA",
    "country": null,
    "country_iso3": null,
    "smt_assignmentgroup": "LAK ICT L2 Support",
    "latitude": null,
    "longitude": null,
    "source": "grafana_fortigate_labels",
    "sub_sites": [
      "LA1"
    ]
  },
  "LIM": {
    "name": "LIM",
    "region": "AMERICAS",
    "country": "Peru",
    "country_iso3": "PER",
    "smt_assignmentgroup": "LIM ICT L2 SUPPORT",
    "latitude": null,
    "longitude": null,
    "source": "grafana_fortigate_labels",
    "sub_sites": [
      "NYC",
      "WAS"
    ]
  },
  "LUH": {
    "name": "LUH",
    "region": "EURASIA",
    "country": null,
    "country_iso3": null,
    "smt_assignmentgroup": "LUH ICT L2 SUPPORT",
    "latitude": null,
    "longitude": null,
    "source": "grafana_fortigate_labels",
    "sub_sites": [
      "RLUH3"
    ]
  },
  "MAN": {
    "name": "MAN",
    "region": "ASIA",
    "country": "Philippines",
    "country_iso3": "PHL",
    "smt_assignmentgroup": "MAN ICT L2 SUPPORT",
    "latitude": 55.0000001,
    "longitude": -97.0000001,
    "source": "grafana_fortigate_labels",
    "sub_sites": [
      "BUU",
      "CAN",
      "R1Q",
      "RMAN9",
      "SUV",
      "TOK",
      "ZAM"
    ]
  },
  "MAP": {
    "name": "MAP",
    "region": "AFRICA East",
    "country": "Mozambique",
    "country_iso3": "MOZ",
    "smt_assignmentgroup": "MAP ICT L2 SUPPORT",
    "latitude": null,
    "longitude": null,
    "source": "grafana_fortigate_labels",
    "sub_sites": [
      "WPEM24"
    ]
  },
  "MAZ": {
    "name": "MAZ",
    "region": "ASIA",
    "country": "Afghanistan",
    "country_iso3": "AFG",
    "smt_assignmentgroup": "MAZ ICT L2 SUPPORT",
    "latitude": null,
    "longitude": null,
    "source": "grafana_fortigate_labels",
    "sub_sites": []
  },
  "MEK": {
    "name": "MEK",
    "region": "AFRICA East",
    "country": "Ethiopia",
    "country_iso3": "ETH",
    "smt_assignmentgroup": "MEK ICT L2 Support",
    "latitude": null,
    "longitude": null,
    "source": "grafana_fortigate_labels",
    "sub_sites": []
  },
  "MEX": {
    "name": "MEX",
    "region": "AMERICAS",
    "country": "Mexico",
    "country_iso3": "MEX",
    "smt_assignmentgroup": "MEX ICT L2 SUPPORT",
    "latitude": null,
    "longitude": null,
    "source": "grafana_fortigate_labels",
    "sub_sites": [
      "SAL",
      "TEG"
    ]
  },
  "MIU": {
    "name": "MIU",
    "region": "AFRICA West",
    "country": null,
    "country_iso3": null,
    "smt_assignmentgroup": "MIU ICT L2 SUPPORT",
    "latitude": null,
    "longitude": null,
    "source": "grafana_fortigate_labels",
    "sub_sites": [
      "BDAT8",
      "DAT",
      "MNG",
      "RDAT01",
      "RMIU02",
      "WMIU6"
    ]
  },
  "MOG": {
    "name": "MOG",
    "region": "AFRICA East",
    "country": "Somalia",
    "country_iso3": "SOM",
    "smt_assignmentgroup": "MOG ICT L2 SUPPORT",
    "latitude": null,
    "longitude": null,
    "source": "grafana_fortigate_labels",
    "sub_sites": [
      "BAD",
      "BEE",
      "BOS",
      "DHO",
      "DHU",
      "GAR",
      "GLK",
      "HAG",
      "JOW",
      "KIS",
      "XUD"
    ]
  },
  "MOH": {
    "name": "MOH",
    "region": "ASIA",
    "country": null,
    "country_iso3": null,
    "smt_assignmentgroup": "MOH ICT L2 SUPPORT",
    "latitude": null,
    "longitude": null,
    "source": "grafana_fortigate_labels",
    "sub_sites": [
      "DBKA1",
      "POM"
    ]
  },
  "MOP": {
    "name": "MOP",
    "region": "AFRICA West",
    "country": "Mali",
    "country_iso3": "MLI",
    "smt_assignmentgroup": "MOP ICT L2 SUPPORT",
    "latitude": null,
    "longitude": null,
    "source": "grafana_fortigate_labels",
    "sub_sites": []
  },
  "MOS": {
    "name": "MOS",
    "region": "EURASIA",
    "country": "Russia",
    "country_iso3": "RUS",
    "smt_assignmentgroup": "MOS ICT L2 SUPPORT",
    "latitude": null,
    "longitude": null,
    "source": "grafana_fortigate_labels",
    "sub_sites": [
      "AMOS1",
      "AMOS2",
      "AMOS3",
      "MSK",
      "TSK"
    ]
  },
  "MOU": {
    "name": "MOU",
    "region": "NAME",
    "country": null,
    "country_iso3": null,
    "smt_assignmentgroup": "MOU ICT L2 SUPPORT",
    "latitude": null,
    "longitude": null,
    "source": "grafana_fortigate_labels",
    "sub_sites": [
      "RMOU05",
      "RMOU12"
    ]
  },
  "MRB": {
    "name": "MRB",
    "region": "NAME",
    "country": null,
    "country_iso3": null,
    "smt_assignmentgroup": "MRB ICT L2 SUPPORT",
    "latitude": null,
    "longitude": null,
    "source": "grafana_fortigate_labels",
    "sub_sites": []
  },
  "MSC": {
    "name": "MSC",
    "region": "ASIA",
    "country": null,
    "country_iso3": null,
    "smt_assignmentgroup": "MSC ICT L2 SUPPORT",
    "latitude": null,
    "longitude": null,
    "source": "grafana_fortigate_labels",
    "sub_sites": []
  },
  "MUB": {
    "name": "MUB",
    "region": "AFRICA West",
    "country": "Nigeria",
    "country_iso3": "NGA",
    "smt_assignmentgroup": "MUB ICT L2 SUPPORT",
    "latitude": null,
    "longitude": null,
    "source": "grafana_fortigate_labels",
    "sub_sites": []
  },
  "NAI": {
    "name": "NAI",
    "region": "AFRICA East",
    "country": "Kenya",
    "country_iso3": "KEN",
    "smt_assignmentgroup": "NAI ICT L2 SUPPORT",
    "latitude": null,
    "longitude": null,
    "source": "grafana_fortigate_labels",
    "sub_sites": [
      "LON",
      "MOM",
      "NA1",
      "NA2",
      "NA3"
    ]
  },
  "NAS": {
    "name": "NAS",
    "region": "NAME",
    "country": null,
    "country_iso3": null,
    "smt_assignmentgroup": "NAS ICT L2 SUPPORT",
    "latitude": null,
    "longitude": null,
    "source": "grafana_fortigate_labels",
    "sub_sites": []
  },
  "NDJ": {
    "name": "NDJ",
    "region": "AFRICA West",
    "country": "Chad",
    "country_iso3": "TCD",
    "smt_assignmentgroup": "NDJ ICT L2 SUPPORT",
    "latitude": null,
    "longitude": null,
    "source": "grafana_fortigate_labels",
    "sub_sites": [
      "ABE",
      "ADR",
      "BGS",
      "NDJR23",
      "NDJR25",
      "RABE",
      "RNDJ24"
    ]
  },
  "NEK": {
    "name": "NEK",
    "region": "AFRICA East",
    "country": "Ethiopia",
    "country_iso3": "ETH",
    "smt_assignmentgroup": "NEK ICT L2 SUPPORT",
    "latitude": null,
    "longitude": null,
    "source": "grafana_fortigate_labels",
    "sub_sites": [
      "HAW"
    ]
  },
  "ODE": {
    "name": "ODE",
    "region": "EURASIA",
    "country": "Ukraine",
    "country_iso3": "UKR",
    "smt_assignmentgroup": "ODE ICT L2 SUPPORT",
    "latitude": null,
    "longitude": null,
    "source": "grafana_fortigate_labels",
    "sub_sites": []
  },
  "OUG": {
    "name": "OUG",
    "region": "AFRICA West",
    "country": "Burkina Faso",
    "country_iso3": "BFA",
    "smt_assignmentgroup": "OUG ICT L2 SUPPORT",
    "latitude": null,
    "longitude": null,
    "source": "grafana_fortigate_labels",
    "sub_sites": [
      "DOI",
      "FDA",
      "OUH"
    ]
  },
  "PAN": {
    "name": "PAN",
    "region": "AMERICAS",
    "country": null,
    "country_iso3": null,
    "smt_assignmentgroup": "PAN ICT L2 SUPPORT",
    "latitude": null,
    "longitude": null,
    "source": "grafana_fortigate_labels",
    "sub_sites": []
  },
  "PAR": {
    "name": "PAR",
    "region": "EURASIA",
    "country": "France",
    "country_iso3": "FRA",
    "smt_assignmentgroup": "PAR ICT L2 SUPPORT",
    "latitude": null,
    "longitude": null,
    "source": "grafana_fortigate_labels",
    "sub_sites": [
      "BRU",
      "LDN"
    ]
  },
  "PEM": {
    "name": "PEM",
    "region": "AFRICA East",
    "country": null,
    "country_iso3": null,
    "smt_assignmentgroup": "PEM ICT L2 SUPPORT",
    "latitude": null,
    "longitude": null,
    "source": "grafana_fortigate_labels",
    "sub_sites": [
      "RMUE2",
      "RPEM33",
      "RPEM37"
    ]
  },
  "PES": {
    "name": "PES",
    "region": "ASIA",
    "country": "Pakistan",
    "country_iso3": "PAK",
    "smt_assignmentgroup": "PES ICT L2 SUPPORT",
    "latitude": null,
    "longitude": null,
    "source": "grafana_fortigate_labels",
    "sub_sites": []
  },
  "POA": {
    "name": "POA",
    "region": "AMERICAS",
    "country": null,
    "country_iso3": null,
    "smt_assignmentgroup": "POA ICT L2 SUPPORT",
    "latitude": null,
    "longitude": null,
    "source": "grafana_fortigate_labels",
    "sub_sites": [
      "RPOA26"
    ]
  },
  "PRE": {
    "name": "PRE",
    "region": "AFRICA East",
    "country": "South Africa",
    "country_iso3": "ZAF",
    "smt_assignmentgroup": "PRE ICT L2 SUPPORT",
    "latitude": null,
    "longitude": null,
    "source": "grafana_fortigate_labels",
    "sub_sites": []
  },
  "PSU": {
    "name": "PSU",
    "region": "AFRICA East",
    "country": null,
    "country_iso3": null,
    "smt_assignmentgroup": "PSU ICT L2 SUPPORT",
    "latitude": null,
    "longitude": null,
    "source": "grafana_fortigate_labels",
    "sub_sites": [
      "ALJ",
      "KHF"
    ]
  },
  "RAM": {
    "name": "RAM",
    "region": "NAME",
    "country": null,
    "country_iso3": null,
    "smt_assignmentgroup": "RAM ICT L2 SUPPORT",
    "latitude": null,
    "longitude": null,
    "source": "grafana_fortigate_labels",
    "sub_sites": [
      "ARAM01",
      "JEN",
      "NAB",
      "TUL"
    ]
  },
  "RD2": {
    "name": "RD2",
    "region": "HQ",
    "country": null,
    "country_iso3": null,
    "smt_assignmentgroup": "TI GVA Proximity Infra",
    "latitude": null,
    "longitude": null,
    "source": "grafana_fortigate_labels",
    "sub_sites": []
  },
  "RD5": {
    "name": "RD5",
    "region": "HQ",
    "country": null,
    "country_iso3": null,
    "smt_assignmentgroup": "TI GVA Proximity Infra",
    "latitude": null,
    "longitude": null,
    "source": "grafana_fortigate_labels",
    "sub_sites": []
  },
  "SAD": {
    "name": "SAD",
    "region": "NAME",
    "country": null,
    "country_iso3": null,
    "smt_assignmentgroup": "SAD ICT L2 SUPPORT",
    "latitude": null,
    "longitude": null,
    "source": "grafana_fortigate_labels",
    "sub_sites": []
  },
  "SAN": {
    "name": "SAN",
    "region": "NAME",
    "country": "Yemen",
    "country_iso3": "YEM",
    "smt_assignmentgroup": "SAN ICT L2 SUPPORT",
    "latitude": 32.544864,
    "longitude": -117.041523,
    "source": "grafana_fortigate_labels",
    "sub_sites": [
      "IBB",
      "RSAN51",
      "WSAN14"
    ]
  },
  "SAR": {
    "name": "SAR",
    "region": "EURASIA",
    "country": "Yemen",
    "country_iso3": "YEM",
    "smt_assignmentgroup": "SAR ICT L2 SUPPORT",
    "latitude": null,
    "longitude": null,
    "source": "grafana_fortigate_labels",
    "sub_sites": [
      "CHS",
      "LUM",
      "PRI"
    ]
  },
  "SIT": {
    "name": "SIT",
    "region": "ASIA",
    "country": null,
    "country_iso3": null,
    "smt_assignmentgroup": "SIT ICT L2 SUPPORT",
    "latitude": null,
    "longitude": null,
    "source": "grafana_fortigate_labels",
    "sub_sites": [
      "MRA"
    ]
  },
  "TAC": {
    "name": "TAC",
    "region": "EURASIA",
    "country": null,
    "country_iso3": null,
    "smt_assignmentgroup": "TAC ICT L2 SUPPORT",
    "latitude": null,
    "longitude": null,
    "source": "grafana_fortigate_labels",
    "sub_sites": [
      "ASA",
      "BIK",
      "DUS",
      "OSH"
    ]
  },
  "TBI": {
    "name": "TBI",
    "region": "EURASIA",
    "country": "Georgia",
    "country_iso3": "GEO",
    "smt_assignmentgroup": "TBI ICT L2 SUPPORT",
    "latitude": null,
    "longitude": null,
    "source": "grafana_fortigate_labels",
    "sub_sites": [
      "SUK"
    ]
  },
  "TBR": {
    "name": "TBR",
    "region": "NAME",
    "country": null,
    "country_iso3": null,
    "smt_assignmentgroup": "TBR ICT L2 SUPPORT",
    "latitude": null,
    "longitude": null,
    "source": "grafana_fortigate_labels",
    "sub_sites": [
      "BTAI5",
      "RTAI7"
    ]
  },
  "TEH": {
    "name": "TEH",
    "region": "NAME",
    "country": "Iran",
    "country_iso3": "IRN",
    "smt_assignmentgroup": "TEH ICT L2 SUPPORT",
    "latitude": null,
    "longitude": null,
    "source": "grafana_fortigate_labels",
    "sub_sites": []
  },
  "TOM": {
    "name": "TOM",
    "region": "AFRICA West",
    "country": "Mali",
    "country_iso3": "MLI",
    "smt_assignmentgroup": "TOM ICT L2 SUPPORT",
    "latitude": null,
    "longitude": null,
    "source": "grafana_fortigate_labels",
    "sub_sites": []
  },
  "TRI": {
    "name": "TRI",
    "region": "AFRICA West",
    "country": null,
    "country_iso3": null,
    "smt_assignmentgroup": "TRI ICT L2 SUPPORT",
    "latitude": null,
    "longitude": null,
    "source": "grafana_fortigate_labels",
    "sub_sites": [
      "SAB"
    ]
  },
  "TUN": {
    "name": "TUN",
    "region": "AFRICA West",
    "country": null,
    "country_iso3": null,
    "smt_assignmentgroup": "TUN ICT L2 SUPPORT",
    "latitude": null,
    "longitude": null,
    "source": "grafana_fortigate_labels",
    "sub_sites": [
      "ALG",
      "RAB",
      "TID"
    ]
  },
  "WSU": {
    "name": "WSU",
    "region": "EURASIA",
    "country": null,
    "country_iso3": null,
    "smt_assignmentgroup": "WSU ICT L2 SUPPORT",
    "latitude": null,
    "longitude": null,
    "source": "grafana_fortigate_labels",
    "sub_sites": []
  },
  "YAN": {
    "name": "YAN",
    "region": "ASIA",
    "country": "Myanmar",
    "country_iso3": "MMR",
    "smt_assignmentgroup": "YAN ICT L2 SUPPORT",
    "latitude": null,
    "longitude": null,
    "source": "grafana_fortigate_labels",
    "sub_sites": [
      "KYA",
      "LSH",
      "MAY",
      "MUA",
      "MYI",
      "NAY",
      "PAH",
      "RYAN01",
      "TGY",
      "WYAN01",
      "YA2"
    ]
  },
  "YAO": {
    "name": "YAO",
    "region": "AFRICA West",
    "country": "Cameroon",
    "country_iso3": "CMR",
    "smt_assignmentgroup": "YAO ICT L2 SUPPORT",
    "latitude": null,
    "longitude": null,
    "source": "grafana_fortigate_labels",
    "sub_sites": [
      "BME",
      "BUX",
      "DOU",
      "KOU",
      "MRO",
      "RBUX2",
      "WYAO01"
    ]
  },
  "YOL": {
    "name": "YOL",
    "region": "AFRICA West",
    "country": "Nigeria",
    "country_iso3": "NGA",
    "smt_assignmentgroup": "YOL ICT L2 SUPPORT",
    "latitude": null,
    "longitude": null,
    "source": "grafana_fortigate_labels",
    "sub_sites": [
      "RBIU02"
    ]
  },
  "BCT": {
    "name": "BCT",
    "region": null,
    "country": null,
    "country_iso3": null,
    "smt_assignmentgroup": "BCT ICT L2 Support",
    "latitude": null,
    "longitude": null,
    "source": "servicenow+grafana",
    "sub_sites": []
  },
  "BME": {
    "name": "BME",
    "region": null,
    "country": null,
    "country_iso3": null,
    "smt_assignmentgroup": "BME ICT L2 Support",
    "latitude": null,
    "longitude": null,
    "source": "servicenow+grafana",
    "sub_sites": []
  },
  "BAH": {
    "name": "BAH",
    "region": null,
    "country": null,
    "country_iso3": null,
    "smt_assignmentgroup": "BAH ICT L2 Support",
    "latitude": null,
    "longitude": null,
    "source": "servicenow+grafana",
    "sub_sites": []
  },
  "BUU": {
    "name": "BUU",
    "region": null,
    "country": null,
    "country_iso3": null,
    "smt_assignmentgroup": "BUU ICT L2 Support",
    "latitude": null,
    "longitude": null,
    "source": "servicenow+grafana",
    "sub_sites": []
  },
  "SUV": {
    "name": "Suva",
    "region": "ASIA",
    "country": "Fiji",
    "country_iso3": "FJI",
    "smt_assignmentgroup": "SUV ICT L2 Support",
    "latitude": null,
    "longitude": null,
    "source": "servicenow+grafana",
    "sub_sites": []
  },
  "LON": {
    "name": "London",
    "region": "AFRICA West",
    "country": "United Kingdom",
    "country_iso3": "GBR",
    "smt_assignmentgroup": "LON ICT L2 Support",
    "latitude": null,
    "longitude": null,
    "source": "servicenow+grafana",
    "sub_sites": [
      "DJI"
    ]
  },
  "UVI": {
    "name": "UVI",
    "region": null,
    "country": "Democratic Republic Of The Congo",
    "country_iso3": null,
    "smt_assignmentgroup": "UVI ICT L2 Support",
    "latitude": null,
    "longitude": null,
    "source": "servicenow+grafana",
    "sub_sites": []
  },
  "POP": {
    "name": "POP",
    "region": null,
    "country": null,
    "country_iso3": null,
    "smt_assignmentgroup": "POP ICT L2 Support",
    "latitude": null,
    "longitude": null,
    "source": "servicenow+grafana",
    "sub_sites": []
  },
  "WAU": {
    "name": "Wau",
    "region": "AFRICA East",
    "country": "South Sudan",
    "country_iso3": "SSD",
    "smt_assignmentgroup": "WAU ICT L2 Support",
    "latitude": null,
    "longitude": null,
    "source": "servicenow+grafana",
    "sub_sites": []
  },
  "BUX": {
    "name": "BUX",
    "region": null,
    "country": null,
    "country_iso3": null,
    "smt_assignmentgroup": "BUX ICT L2 Support",
    "latitude": null,
    "longitude": null,
    "source": "servicenow+grafana",
    "sub_sites": []
  },
  "ABE": {
    "name": "ABE",
    "region": null,
    "country": null,
    "country_iso3": null,
    "smt_assignmentgroup": "ABE ICT L2 Support",
    "latitude": null,
    "longitude": null,
    "source": "servicenow+grafana",
    "sub_sites": []
  },
  "MRA": {
    "name": "MRA",
    "region": null,
    "country": null,
    "country_iso3": null,
    "smt_assignmentgroup": "MRA ICT L2 Support",
    "latitude": null,
    "longitude": null,
    "source": "servicenow+grafana",
    "sub_sites": []
  },
  "TGY": {
    "name": "TGY",
    "region": null,
    "country": null,
    "country_iso3": null,
    "smt_assignmentgroup": "TGY ICT L2 Support",
    "latitude": null,
    "longitude": null,
    "source": "servicenow+grafana",
    "sub_sites": []
  },
  "OSH": {
    "name": "OSH",
    "region": null,
    "country": null,
    "country_iso3": null,
    "smt_assignmentgroup": "OSH ICT L2 Support",
    "latitude": null,
    "longitude": null,
    "source": "servicenow+grafana",
    "sub_sites": []
  },
  "SOK": {
    "name": "SOK",
    "region": null,
    "country": null,
    "country_iso3": null,
    "smt_assignmentgroup": "SOK ICT L2 Support",
    "latitude": null,
    "longitude": null,
    "source": "servicenow+grafana",
    "sub_sites": []
  },
  "MAY": {
    "name": "MAY",
    "region": null,
    "country": null,
    "country_iso3": null,
    "smt_assignmentgroup": "MAY ICT L2 Support",
    "latitude": null,
    "longitude": null,
    "source": "servicenow+grafana",
    "sub_sites": []
  },
  "OUH": {
    "name": "OUH",
    "region": null,
    "country": null,
    "country_iso3": null,
    "smt_assignmentgroup": "OUH ICT L2 Support",
    "latitude": null,
    "longitude": null,
    "source": "servicenow+grafana",
    "sub_sites": []
  },
  "YEI": {
    "name": "Yei",
    "region": "AFRICA East",
    "country": "South Sudan",
    "country_iso3": "SSD",
    "smt_assignmentgroup": "YEI ICT L2 Support",
    "latitude": null,
    "longitude": null,
    "source": "servicenow+grafana",
    "sub_sites": []
  },
  "LVI": {
    "name": "LVI",
    "region": null,
    "country": "Ukraine",
    "country_iso3": "UKR",
    "smt_assignmentgroup": "LVI ICT L2 Support",
    "latitude": null,
    "longitude": null,
    "source": "servicenow+grafana",
    "sub_sites": []
  },
  "TEG": {
    "name": "Tegucigalpa",
    "region": "AMERICAS",
    "country": "Honduras",
    "country_iso3": "HND",
    "smt_assignmentgroup": "TEG ICT L2 Support",
    "latitude": null,
    "longitude": null,
    "source": "servicenow+grafana",
    "sub_sites": []
  },
  "DAT": {
    "name": "DAT",
    "region": null,
    "country": null,
    "country_iso3": null,
    "smt_assignmentgroup": "DAT ICT L2 Support",
    "latitude": null,
    "longitude": null,
    "source": "servicenow+grafana",
    "sub_sites": []
  },
  "DSS": {
    "name": "DSS",
    "region": null,
    "country": null,
    "country_iso3": null,
    "smt_assignmentgroup": "DSS ICT L2 Support",
    "latitude": null,
    "longitude": null,
    "source": "servicenow+grafana",
    "sub_sites": []
  },
  "BIK": {
    "name": "BIK",
    "region": null,
    "country": null,
    "country_iso3": null,
    "smt_assignmentgroup": "BIK ICT L2 Support",
    "latitude": null,
    "longitude": null,
    "source": "servicenow+grafana",
    "sub_sites": []
  },
  "BLC": {
    "name": "BLC",
    "region": null,
    "country": null,
    "country_iso3": null,
    "smt_assignmentgroup": "BLC ICT L2 Support",
    "latitude": null,
    "longitude": null,
    "source": "servicenow+grafana",
    "sub_sites": []
  },
  "JAL": {
    "name": "JAL",
    "region": null,
    "country": null,
    "country_iso3": null,
    "smt_assignmentgroup": "JAL ICT L2 Support",
    "latitude": null,
    "longitude": null,
    "source": "servicenow+grafana",
    "sub_sites": []
  },
  "MYI": {
    "name": "MYI",
    "region": null,
    "country": "Myanmar",
    "country_iso3": "MMR",
    "smt_assignmentgroup": "MYI ICT L2 Support",
    "latitude": null,
    "longitude": null,
    "source": "servicenow+grafana",
    "sub_sites": []
  },
  "PUA": {
    "name": "PUA",
    "region": null,
    "country": null,
    "country_iso3": null,
    "smt_assignmentgroup": "PUA ICT L2 Support",
    "latitude": null,
    "longitude": null,
    "source": "servicenow+grafana",
    "sub_sites": []
  },
  "FLO": {
    "name": "FLO",
    "region": null,
    "country": "Usa",
    "country_iso3": "USA",
    "smt_assignmentgroup": "FLO ICT L2 Support",
    "latitude": 37.09024,
    "longitude": -95.712891,
    "source": "servicenow+grafana",
    "sub_sites": []
  },
  "SCI": {
    "name": "SCI",
    "region": null,
    "country": null,
    "country_iso3": null,
    "smt_assignmentgroup": "SCI ICT L2 Support",
    "latitude": null,
    "longitude": null,
    "source": "servicenow+grafana",
    "sub_sites": []
  },
  "MAL": {
    "name": "Malakal",
    "region": "AFRICA East",
    "country": "South Sudan",
    "country_iso3": "SSD",
    "smt_assignmentgroup": "MAL ICT L2 Support",
    "latitude": null,
    "longitude": null,
    "source": "servicenow+grafana",
    "sub_sites": []
  },
  "EBL": {
    "name": "EBL",
    "region": null,
    "country": null,
    "country_iso3": null,
    "smt_assignmentgroup": "EBL ICT L2 Support",
    "latitude": null,
    "longitude": null,
    "source": "servicenow+grafana",
    "sub_sites": []
  },
  "TYR": {
    "name": "TYR",
    "region": null,
    "country": null,
    "country_iso3": null,
    "smt_assignmentgroup": "TYR ICT L2 Support",
    "latitude": null,
    "longitude": null,
    "source": "servicenow+grafana",
    "sub_sites": []
  },
  "SMM": {
    "name": "SMM",
    "region": null,
    "country": null,
    "country_iso3": null,
    "smt_assignmentgroup": "SMM ICT L2 Support",
    "latitude": null,
    "longitude": null,
    "source": "servicenow+grafana",
    "sub_sites": []
  },
  "AMW": {
    "name": "AMW",
    "region": null,
    "country": null,
    "country_iso3": null,
    "smt_assignmentgroup": "AMW ICT L2 Support",
    "latitude": null,
    "longitude": null,
    "source": "servicenow+grafana",
    "sub_sites": []
  },
  "KIS": {
    "name": "KIS",
    "region": null,
    "country": null,
    "country_iso3": null,
    "smt_assignmentgroup": "KIS ICT L2 Support",
    "latitude": null,
    "longitude": null,
    "source": "servicenow+grafana",
    "sub_sites": [
      "XUD"
    ]
  },
  "MEE": {
    "name": "MEE",
    "region": null,
    "country": null,
    "country_iso3": null,
    "smt_assignmentgroup": "MEE ICT L2 Support",
    "latitude": null,
    "longitude": null,
    "source": "servicenow+grafana",
    "sub_sites": []
  },
  "HAW": {
    "name": "HAW",
    "region": null,
    "country": null,
    "country_iso3": null,
    "smt_assignmentgroup": "HAW ICT L2 Support",
    "latitude": null,
    "longitude": null,
    "source": "servicenow+grafana",
    "sub_sites": []
  },
  "GUL": {
    "name": "GUL",
    "region": null,
    "country": null,
    "country_iso3": null,
    "smt_assignmentgroup": "GUL ICT L2 Support",
    "latitude": null,
    "longitude": null,
    "source": "servicenow+grafana",
    "sub_sites": []
  },
  "MUA": {
    "name": "MUA",
    "region": null,
    "country": null,
    "country_iso3": null,
    "smt_assignmentgroup": "MUA ICT L2 Support",
    "latitude": null,
    "longitude": null,
    "source": "servicenow+grafana",
    "sub_sites": []
  },
  "SYJ": {
    "name": "SYJ",
    "region": null,
    "country": null,
    "country_iso3": null,
    "smt_assignmentgroup": "SYJ ICT L2 Support",
    "latitude": null,
    "longitude": null,
    "source": "servicenow+grafana",
    "sub_sites": []
  },
  "LOM": {
    "name": "LOM",
    "region": null,
    "country": "Togo",
    "country_iso3": "TGO",
    "smt_assignmentgroup": "LOM ICT L2 Support",
    "latitude": null,
    "longitude": null,
    "source": "servicenow+grafana",
    "sub_sites": []
  },
  "ZAH": {
    "name": "ZAH",
    "region": null,
    "country": null,
    "country_iso3": null,
    "smt_assignmentgroup": "ZAH ICT L2 Support",
    "latitude": null,
    "longitude": null,
    "source": "servicenow+grafana",
    "sub_sites": []
  },
  "KYN": {
    "name": "KYN",
    "region": null,
    "country": null,
    "country_iso3": null,
    "smt_assignmentgroup": "KYN ICT L2 Support",
    "latitude": null,
    "longitude": null,
    "source": "servicenow+grafana",
    "sub_sites": []
  },
  "MOM": {
    "name": "MOM",
    "region": null,
    "country": null,
    "country_iso3": null,
    "smt_assignmentgroup": "MOM ICT L2 Support",
    "latitude": null,
    "longitude": null,
    "source": "servicenow+grafana",
    "sub_sites": []
  },
  "CTN": {
    "name": "CTN",
    "region": null,
    "country": null,
    "country_iso3": null,
    "smt_assignmentgroup": "CTN ICT L2 Support",
    "latitude": null,
    "longitude": null,
    "source": "servicenow+grafana",
    "sub_sites": []
  },
  "BGS": {
    "name": "BGS",
    "region": null,
    "country": null,
    "country_iso3": null,
    "smt_assignmentgroup": "BGS ICT L2 Support",
    "latitude": null,
    "longitude": null,
    "source": "servicenow+grafana",
    "sub_sites": []
  },
  "SEO": {
    "name": "SEO",
    "region": null,
    "country": null,
    "country_iso3": null,
    "smt_assignmentgroup": "SEO ICT L2 Support",
    "latitude": null,
    "longitude": null,
    "source": "servicenow+grafana",
    "sub_sites": []
  },
  "CAN": {
    "name": "CAN",
    "region": null,
    "country": null,
    "country_iso3": null,
    "smt_assignmentgroup": "CAN ICT L2 Support",
    "latitude": null,
    "longitude": null,
    "source": "servicenow+grafana",
    "sub_sites": []
  },
  "SAA": {
    "name": "SAA",
    "region": null,
    "country": null,
    "country_iso3": null,
    "smt_assignmentgroup": "SAA ICT L2 Support",
    "latitude": null,
    "longitude": null,
    "source": "servicenow+grafana",
    "sub_sites": []
  },
  "BON": {
    "name": "BON",
    "region": null,
    "country": null,
    "country_iso3": null,
    "smt_assignmentgroup": "BON ICT L2 Support",
    "latitude": null,
    "longitude": null,
    "source": "servicenow+grafana",
    "sub_sites": []
  },
  "LSH": {
    "name": "LSH",
    "region": null,
    "country": null,
    "country_iso3": null,
    "smt_assignmentgroup": "LSH ICT L2 Support",
    "latitude": null,
    "longitude": null,
    "source": "servicenow+grafana",
    "sub_sites": []
  },
  "JMH": {
    "name": "JMH",
    "region": null,
    "country": null,
    "country_iso3": null,
    "smt_assignmentgroup": "JMH ICT L2 Support",
    "latitude": null,
    "longitude": null,
    "source": "servicenow+grafana",
    "sub_sites": []
  },
  "ALG": {
    "name": "ALG",
    "region": null,
    "country": null,
    "country_iso3": null,
    "smt_assignmentgroup": "ALG ICT L2 Support",
    "latitude": null,
    "longitude": null,
    "source": "servicenow+grafana",
    "sub_sites": []
  },
  "FAI": {
    "name": "FAI",
    "region": null,
    "country": null,
    "country_iso3": null,
    "smt_assignmentgroup": "FAI ICT L2 Support",
    "latitude": null,
    "longitude": null,
    "source": "servicenow+grafana",
    "sub_sites": []
  },
  "KYA": {
    "name": "KYA",
    "region": null,
    "country": "Myanmar",
    "country_iso3": "MMR",
    "smt_assignmentgroup": "KYA ICT L2 Support",
    "latitude": null,
    "longitude": null,
    "source": "servicenow+grafana",
    "sub_sites": []
  },
  "PPO": {
    "name": "PPO",
    "region": null,
    "country": null,
    "country_iso3": null,
    "smt_assignmentgroup": "PPO ICT L2 Support",
    "latitude": null,
    "longitude": null,
    "source": "servicenow+grafana",
    "sub_sites": []
  },
  "TOK": {
    "name": "TOK",
    "region": null,
    "country": null,
    "country_iso3": null,
    "smt_assignmentgroup": "TOK ICT L2 Support",
    "latitude": null,
    "longitude": null,
    "source": "servicenow+grafana",
    "sub_sites": []
  },
  "TRC": {
    "name": "TRC",
    "region": null,
    "country": null,
    "country_iso3": null,
    "smt_assignmentgroup": "TRC ICT L2 Support",
    "latitude": null,
    "longitude": null,
    "source": "servicenow+grafana",
    "sub_sites": []
  },
  "EBA": {
    "name": "EBA",
    "region": null,
    "country": null,
    "country_iso3": null,
    "smt_assignmentgroup": "EBA ICT L2 Support",
    "latitude": null,
    "longitude": null,
    "source": "servicenow+grafana",
    "sub_sites": []
  },
  "DOI": {
    "name": "Donetsk",
    "region": "EURASIA",
    "country": "Ukraine",
    "country_iso3": "UKR",
    "smt_assignmentgroup": "DOI ICT L2 Support",
    "latitude": null,
    "longitude": null,
    "source": "servicenow+grafana",
    "sub_sites": []
  },
  "KOU": {
    "name": "KOU",
    "region": null,
    "country": "Cameroon",
    "country_iso3": "CMR",
    "smt_assignmentgroup": "KOU ICT L2 Support",
    "latitude": null,
    "longitude": null,
    "source": "servicenow+grafana",
    "sub_sites": []
  },
  "HOM": {
    "name": "HOM",
    "region": null,
    "country": "Syria",
    "country_iso3": "SYR",
    "smt_assignmentgroup": "HOM ICT L2 Support",
    "latitude": null,
    "longitude": null,
    "source": "servicenow+grafana",
    "sub_sites": []
  },
  "DJB": {
    "name": "DJB",
    "region": null,
    "country": null,
    "country_iso3": null,
    "smt_assignmentgroup": "DJB ICT L2 Support",
    "latitude": null,
    "longitude": null,
    "source": "servicenow+grafana",
    "sub_sites": []
  },
  "JIJ": {
    "name": "JIJ",
    "region": null,
    "country": null,
    "country_iso3": null,
    "smt_assignmentgroup": "JIJ ICT L2 Support",
    "latitude": null,
    "longitude": null,
    "source": "servicenow+grafana",
    "sub_sites": []
  },
  "WAS": {
    "name": "Washington",
    "region": "AMERICAS",
    "country": "United States",
    "country_iso3": "USA",
    "smt_assignmentgroup": "WAS ICT L2 Support",
    "latitude": null,
    "longitude": null,
    "source": "servicenow+grafana",
    "sub_sites": []
  },
  "HAG": {
    "name": "HAG",
    "region": null,
    "country": null,
    "country_iso3": null,
    "smt_assignmentgroup": "HAG ICT L2 Support",
    "latitude": null,
    "longitude": null,
    "source": "servicenow+grafana",
    "sub_sites": []
  },
  "CHS": {
    "name": "CHS",
    "region": null,
    "country": null,
    "country_iso3": null,
    "smt_assignmentgroup": "CHS ICT L2 Support",
    "latitude": null,
    "longitude": null,
    "source": "servicenow+grafana",
    "sub_sites": []
  },
  "ALJ": {
    "name": "ALJ",
    "region": null,
    "country": null,
    "country_iso3": null,
    "smt_assignmentgroup": "ALJ ICT L2 Support",
    "latitude": null,
    "longitude": null,
    "source": "servicenow+grafana",
    "sub_sites": []
  },
  "KBA": {
    "name": "KBA",
    "region": null,
    "country": null,
    "country_iso3": null,
    "smt_assignmentgroup": "KBA ICT L2 Support",
    "latitude": null,
    "longitude": null,
    "source": "servicenow+grafana",
    "sub_sites": []
  },
  "PAH": {
    "name": "PAH",
    "region": null,
    "country": null,
    "country_iso3": null,
    "smt_assignmentgroup": "PAH ICT L2 Support",
    "latitude": null,
    "longitude": null,
    "source": "servicenow+grafana",
    "sub_sites": []
  },
  "NYC": {
    "name": "NYC",
    "region": null,
    "country": null,
    "country_iso3": null,
    "smt_assignmentgroup": "NYC ICT L2 Support",
    "latitude": null,
    "longitude": null,
    "source": "servicenow+grafana",
    "sub_sites": []
  },
  "BMB": {
    "name": "BMB",
    "region": null,
    "country": null,
    "country_iso3": null,
    "smt_assignmentgroup": "BMB ICT L2 Support",
    "latitude": null,
    "longitude": null,
    "source": "servicenow+grafana",
    "sub_sites": []
  },
  "BGD": {
    "name": "BGD",
    "region": null,
    "country": null,
    "country_iso3": null,
    "smt_assignmentgroup": "BGD ICT L2 Support",
    "latitude": null,
    "longitude": null,
    "source": "servicenow+grafana",
    "sub_sites": []
  },
  "TEL": {
    "name": "Tel Aviv",
    "region": "NAME",
    "country": "Israel",
    "country_iso3": "ISR",
    "smt_assignmentgroup": "TEL ICT L2 Support",
    "latitude": null,
    "longitude": null,
    "source": "servicenow+grafana",
    "sub_sites": []
  },
  "QUB": {
    "name": "QUB",
    "region": null,
    "country": null,
    "country_iso3": null,
    "smt_assignmentgroup": "QUB ICT L2 Support",
    "latitude": null,
    "longitude": null,
    "source": "servicenow+grafana",
    "sub_sites": []
  },
  "DUS": {
    "name": "Dushanbe",
    "region": "EURASIA",
    "country": "Tajikistan",
    "country_iso3": "TJK",
    "smt_assignmentgroup": "DUS ICT L2 Support",
    "latitude": null,
    "longitude": null,
    "source": "servicenow+grafana",
    "sub_sites": []
  },
  "CUC": {
    "name": "CUC",
    "region": null,
    "country": null,
    "country_iso3": null,
    "smt_assignmentgroup": "CUC ICT L2 Support",
    "latitude": null,
    "longitude": null,
    "source": "servicenow+grafana",
    "sub_sites": []
  },
  "GAR": {
    "name": "GAR",
    "region": null,
    "country": null,
    "country_iso3": null,
    "smt_assignmentgroup": "GAR ICT L2 Support",
    "latitude": null,
    "longitude": null,
    "source": "servicenow+grafana",
    "sub_sites": []
  },
  "FDA": {
    "name": "FDA",
    "region": null,
    "country": null,
    "country_iso3": null,
    "smt_assignmentgroup": "FDA ICT L2 Support",
    "latitude": null,
    "longitude": null,
    "source": "servicenow+grafana",
    "sub_sites": []
  },
  "RAD": {
    "name": "RAD",
    "region": null,
    "country": null,
    "country_iso3": null,
    "smt_assignmentgroup": "RAD ICT L2 Support",
    "latitude": null,
    "longitude": null,
    "source": "servicenow+grafana",
    "sub_sites": []
  },
  "DAR": {
    "name": "Dar es Salaam",
    "region": "AFRICA East",
    "country": "Tanzania",
    "country_iso3": "TZA",
    "smt_assignmentgroup": "DAR ICT L2 Support",
    "latitude": null,
    "longitude": null,
    "source": "servicenow+grafana",
    "sub_sites": []
  },
  "ADO": {
    "name": "ADO",
    "region": null,
    "country": null,
    "country_iso3": null,
    "smt_assignmentgroup": "ADO ICT L2 Support",
    "latitude": null,
    "longitude": null,
    "source": "servicenow+grafana",
    "sub_sites": []
  },
  "JOS": {
    "name": "JOS",
    "region": null,
    "country": null,
    "country_iso3": null,
    "smt_assignmentgroup": "JOS ICT L2 Support",
    "latitude": null,
    "longitude": null,
    "source": "servicenow+grafana",
    "sub_sites": []
  },
  "FOZ": {
    "name": "FOZ",
    "region": null,
    "country": null,
    "country_iso3": null,
    "smt_assignmentgroup": "FOZ ICT L2 Support",
    "latitude": null,
    "longitude": null,
    "source": "servicenow+grafana",
    "sub_sites": []
  },
  "SAO": {
    "name": "SAO",
    "region": null,
    "country": null,
    "country_iso3": null,
    "smt_assignmentgroup": "SAO ICT L2 Support",
    "latitude": null,
    "longitude": null,
    "source": "servicenow+grafana",
    "sub_sites": []
  },
  "BAD": {
    "name": "BAD",
    "region": null,
    "country": null,
    "country_iso3": null,
    "smt_assignmentgroup": "BAD ICT L2 Support",
    "latitude": null,
    "longitude": null,
    "source": "servicenow+grafana",
    "sub_sites": []
  },
  "BAK": {
    "name": "Baku",
    "region": "EURASIA",
    "country": "Azerbaijan",
    "country_iso3": "AZE",
    "smt_assignmentgroup": "BAK ICT L2 Support",
    "latitude": null,
    "longitude": null,
    "source": "servicenow+grafana",
    "sub_sites": []
  },
  "MIR": {
    "name": "MIR",
    "region": null,
    "country": null,
    "country_iso3": null,
    "smt_assignmentgroup": "MIR ICT L2 Support",
    "latitude": null,
    "longitude": null,
    "source": "servicenow+grafana",
    "sub_sites": []
  },
  "MRO": {
    "name": "MRO",
    "region": null,
    "country": null,
    "country_iso3": null,
    "smt_assignmentgroup": "MRO ICT L2 Support",
    "latitude": null,
    "longitude": null,
    "source": "servicenow+grafana",
    "sub_sites": []
  },
  "TSK": {
    "name": "TSK",
    "region": null,
    "country": null,
    "country_iso3": null,
    "smt_assignmentgroup": "TSK ICT L2 Support",
    "latitude": null,
    "longitude": null,
    "source": "servicenow+grafana",
    "sub_sites": []
  },
  "DAP": {
    "name": "DAP",
    "region": null,
    "country": "Togo",
    "country_iso3": "TGO",
    "smt_assignmentgroup": "DAP ICT L2 Support",
    "latitude": null,
    "longitude": null,
    "source": "servicenow+grafana",
    "sub_sites": []
  },
  "ALC": {
    "name": "ALC",
    "region": null,
    "country": null,
    "country_iso3": null,
    "smt_assignmentgroup": "ALC ICT L2 Support",
    "latitude": null,
    "longitude": null,
    "source": "servicenow+grafana",
    "sub_sites": []
  },
  "BUA": {
    "name": "BUA",
    "region": null,
    "country": null,
    "country_iso3": null,
    "smt_assignmentgroup": "BUA ICT L2 Support",
    "latitude": null,
    "longitude": null,
    "source": "servicenow+grafana",
    "sub_sites": []
  },
  "DOU": {
    "name": "DOU",
    "region": null,
    "country": null,
    "country_iso3": null,
    "smt_assignmentgroup": "DOU ICT L2 Support",
    "latitude": null,
    "longitude": null,
    "source": "servicenow+grafana",
    "sub_sites": []
  },
  "YES": {
    "name": "YES",
    "region": null,
    "country": null,
    "country_iso3": null,
    "smt_assignmentgroup": "YES ICT L2 Support",
    "latitude": null,
    "longitude": null,
    "source": "servicenow+grafana",
    "sub_sites": []
  },
  "KUD": {
    "name": "KUD",
    "region": null,
    "country": null,
    "country_iso3": null,
    "smt_assignmentgroup": "KUD ICT L2 Support",
    "latitude": null,
    "longitude": null,
    "source": "servicenow+grafana",
    "sub_sites": []
  }
}